[
  {
    "_id": "q_gk2022_fusheng_2022年国家公务员考试行测真题副省级_001",
    "module_id": "mod_data",
    "type": "single",
    "difficulty": "中等",
    "source": "国考真题",
    "year": 2022,
    "paper_id": "gk2022_fusheng_2022年国家公务员考试行测真题副省级",
    "paper_name": "2022年国家公务员考试《行测》真题（副省级)",
    "province": "国家",
    "position": "副省级",
    "paper_date": "",
    "question_number": 1,
    "content": "万批次的食品类别有12 个\n③糕点类食品的抽检合格量是不合格量的",
    "stem_images": [],
    "material": "几项？\n①蔬菜、水果制品的总体抽检合格率高于95%\n②样品抽检量超过",
    "material_images": [],
    "options": [
      "A",
      "B",
      "C",
      "D"
    ],
    "option_images": [
      [],
      [],
      [],
      []
    ],
    "answer": 3,
    "explanation": "1.解析\n第一步，本题考查时政。\n第二步，2021 年7 月1 日,习近平总书记在庆祝中国共产党成立100 周年大会上的讲话指出，新民主主义革命的胜利，彻底结束了旧中国半殖民地半封建社会的历史，彻底结束了旧中国一盘散沙的局面，彻底废除了列强强加给中国的不平等条约和帝国主义在中国的一切特权，为实现中华民族伟大复兴创造了根本社会条件。②③④正确。\n因此，选择D 选项。\n拓展\n①：2021 年7 月1 日,习近平总书记在庆祝中国共产党成立100 周年大会上的讲话指出，为了实现中华民族伟大复兴，中国共产党团结带领中国人民，自力更生、发愤图强，创造了社会主义革命和建设的伟大成就。我们进行社会主义革命，消灭在中国延续几千年的封建剥削压迫制度，确立社会主义基本制度，推进社会主义建设，战胜帝国主义、霸权主义的颠覆破坏和武装挑衅，实现了中华民族有史以来最为广泛而深刻的社会变革。选项应为社会主义革命和建设时期的成就，故①错误。",
    "explanation_images": [],
    "tags": [
      "资料分析"
    ],
    "status": "enabled"
  },
  {
    "_id": "q_gk2022_fusheng_2022年国家公务员考试行测真题副省级_120",
    "module_id": "mod_data",
    "type": "single",
    "difficulty": "中等",
    "source": "国考真题",
    "year": 2022,
    "paper_id": "gk2022_fusheng_2022年国家公务员考试行测真题副省级",
    "paper_name": "2022年国家公务员考试《行测》真题（副省级)",
    "province": "国家",
    "position": "副省级",
    "paper_date": "",
    "question_number": 120,
    "content": "（单选题）已知2020 年中国IC 封装市场规模同比增长x 亿元，IC 封装市场中IC 先进封装市场规模占比同比增长y 个百分点，而2020 年往后中国IC 封装市场规模及IC 先进封装市场规模占比每年都分别同比增长x 亿元和y 个百分点，则到“十四五”最后一年（2025 年），中国IC 先进封装市场规模将达到多少亿元?",
    "stem_images": [],
    "material": "",
    "material_images": [
      "/assets/question-images/word-bank/gk2022_fusheng_2022年国家公务员考试行测真题副省级_0021_rId29.png"
    ],
    "options": [
      "469",
      "575",
      "433",
      "521"
    ],
    "option_images": [
      [],
      [],
      [],
      []
    ],
    "answer": 3,
    "explanation": "120.解析\n第 60 页共 64 页\n第一步，本题考查现期量计算。\n第二步，定位图形材料。\n第三步，根据增长量=现期量-基期量，由柱状图可知，2020 年中国IC 封装市场规模同比增长x 亿元，x=2478.9-2349.7≈2479-2350=129。由折线图可知，2020 年IC 封装市场中的IC 先进封装市场规模占比同比增长y 个百分点，y=13.26-12.58=0.68。\n第四步，根据末期量=初期量+年均增长量×相差年数以及题干“2020 年往后中国IC 封装市场规模及IC 先进封装市场规模占比每年都分别增长x 亿元和y 个百分点”，则“十四五”最后一年，2025 年中国IC 封装市场规模≈2479+129×5=2479+645=3124 亿元，2025 年IC 先进封装市场规模占比 =13.26%+0.68%×5=13.26%+3.4%=16.66%。根据部分量=整体量×比重，2025 年IC 先进封装市场规模\n=3124×16.66%≈3124×因此，选择D 选项。 ≈520（亿元），最接近D 选项。",
    "explanation_images": [
      "/assets/question-images/word-bank/gk2022_fusheng_2022年国家公务员考试行测真题副省级_answer_0037_rId38.png"
    ],
    "tags": [
      "资料分析"
    ],
    "status": "enabled"
  },
  {
    "_id": "q_gk2022_fusheng_2022年国家公务员考试行测真题副省级_130",
    "module_id": "mod_data",
    "type": "single",
    "difficulty": "中等",
    "source": "国考真题",
    "year": 2022,
    "paper_id": "gk2022_fusheng_2022年国家公务员考试行测真题副省级",
    "paper_name": "2022年国家公务员考试《行测》真题（副省级)",
    "province": "国家",
    "position": "副省级",
    "paper_date": "",
    "question_number": 130,
    "content": "（单选题）2020 年，H 省农民老王在承包地中种植秋粮玉米，按全省平均生产成本估算，他在种子和农\n药上需要花费2000 元。如亦按全省平均生产成本估算，他需要花费的人工成本在以下哪个范围内？",
    "stem_images": [],
    "material": "的是：",
    "material_images": [],
    "options": [
      "不到2000 元",
      "2000—2500 元之间",
      "2500—3000 元之间",
      "超过3000 元"
    ],
    "option_images": [
      [],
      [],
      [],
      []
    ],
    "answer": 2,
    "explanation": "130.解析\n第一步，本题考查现期平均数计算。\n第二步，定位表格材料，玉米的种子生产成本48.5 元/亩、农药生产成本25.6 元/亩、人工成本104.4 元/亩。\n第三步，根据平均生产成本=总成本÷亩数，数据本身不大，简单取整，可得老王的土地亩数为\n亩，则需要的人工成本为27×104.4≈27×100+27×4.4≈2700+108≈ 项范围内。 元，在C 选\n因此，选择C 选项。",
    "explanation_images": [
      "/assets/question-images/word-bank/gk2022_fusheng_2022年国家公务员考试行测真题副省级_answer_0055_rId55.png",
      "/assets/question-images/word-bank/gk2022_fusheng_2022年国家公务员考试行测真题副省级_answer_0056_rId56.png"
    ],
    "tags": [
      "资料分析"
    ],
    "status": "enabled"
  },
  {
    "_id": "q_gk2022_fusheng_2022年国家公务员考试行测真题副省级_116",
    "module_id": "mod_data",
    "type": "single",
    "difficulty": "中等",
    "source": "国考真题",
    "year": 2022,
    "paper_id": "gk2022_fusheng_2022年国家公务员考试行测真题副省级",
    "paper_name": "2022年国家公务员考试《行测》真题（副省级)",
    "province": "国家",
    "position": "副省级",
    "paper_date": "",
    "question_number": 116,
    "content": "（单选题）2019 年，中国IC 先进封装市场规模约为多少亿元？",
    "stem_images": [],
    "material": "",
    "material_images": [
      "/assets/question-images/word-bank/gk2022_fusheng_2022年国家公务员考试行测真题副省级_0021_rId29.png"
    ],
    "options": [
      "296",
      "279",
      "252",
      "235"
    ],
    "option_images": [
      [],
      [],
      [],
      []
    ],
    "answer": 0,
    "explanation": "116.解析\n第一步，本题考查现期比重计算中的求部分量。\n第二步，定位图形材料，2019 年IC 封装市场规模为2349.7 亿元，IC 先进封装市场规模占比为12.58%。\n第三步，根据部分量=整体量×比重，代入数据可得2019 年，中国IC 先进封装市场规模为\n2349.7×12.58%≈2350×因此，选择A 选项。 ≈294（亿元），A 选项最接近。",
    "explanation_images": [
      "/assets/question-images/word-bank/gk2022_fusheng_2022年国家公务员考试行测真题副省级_answer_0036_rId37.png"
    ],
    "tags": [
      "资料分析"
    ],
    "status": "enabled"
  },
  {
    "_id": "q_gk2022_fusheng_2022年国家公务员考试行测真题副省级_117",
    "module_id": "mod_data",
    "type": "single",
    "difficulty": "中等",
    "source": "国考真题",
    "year": 2022,
    "paper_id": "gk2022_fusheng_2022年国家公务员考试行测真题副省级",
    "paper_name": "2022年国家公务员考试《行测》真题（副省级)",
    "province": "国家",
    "position": "副省级",
    "paper_date": "",
    "question_number": 117,
    "content": "（单选题）“十三五”（2016—2020）年期间，中国IC 封装市场总规模：",
    "stem_images": [],
    "material": "",
    "material_images": [
      "/assets/question-images/word-bank/gk2022_fusheng_2022年国家公务员考试行测真题副省级_0021_rId29.png"
    ],
    "options": [
      "不到1.0 万亿元 B.在1.0—1.1 万亿元之间",
      "",
      "在1.1—1.2 万亿元之间 D.超过1.2 万亿元",
      ""
    ],
    "option_images": [
      [],
      [],
      [],
      []
    ],
    "answer": 1,
    "explanation": "117.解析\n第一步，本题考查简单计算中的和差类。\n第二步，定位图形材料，2016—2020 年中国IC 封装市场总规模分别为1564.3、1889.7、2193.9、2349.7、2478.9 亿元。\n第三步，和差类问题，对数据进行截位舍相同处理，代入数据得2016—2020 年中国IC 封装市场总规模约为156＋189＋219＋235＋248=200×5＋（－44－11＋19＋35＋48）=1000+47=1047，即10470 亿元=1.047万亿元，在B 选项范围内。\n因此，选择B 选项。",
    "explanation_images": [],
    "tags": [
      "资料分析"
    ],
    "status": "enabled"
  },
  {
    "_id": "q_gk2022_fusheng_2022年国家公务员考试行测真题副省级_118",
    "module_id": "mod_data",
    "type": "single",
    "difficulty": "中等",
    "source": "国考真题",
    "year": 2022,
    "paper_id": "gk2022_fusheng_2022年国家公务员考试行测真题副省级",
    "paper_name": "2022年国家公务员考试《行测》真题（副省级)",
    "province": "国家",
    "position": "副省级",
    "paper_date": "",
    "question_number": 118,
    "content": "（单选题）2012—2020 年，中国IC 封装市场中IC 先进封装市场规模占比同比提升1 个百分点以上的年份有几个？",
    "stem_images": [],
    "material": "",
    "material_images": [
      "/assets/question-images/word-bank/gk2022_fusheng_2022年国家公务员考试行测真题副省级_0021_rId29.png"
    ],
    "options": [
      "2",
      "3",
      "4",
      "5"
    ],
    "option_images": [
      [],
      [],
      [],
      []
    ],
    "answer": 0,
    "explanation": "118.解析\n第一步，本题考查简单比较中的读数比较。\n第二步，定位图形材料中的折线图。\n第三步，直接读数可得2012—2020 年，中国IC 封装市场中IC 先进封装市场规模占比同比提升1 个百分点以上的有2012 年（5.65%－4.12%＞1%）和2015 年（9.91%－7.37%＞1%），共2 个年份，其余年份均不符合。因此，选择A 选项。",
    "explanation_images": [],
    "tags": [
      "资料分析"
    ],
    "status": "enabled"
  },
  {
    "_id": "q_gk2022_fusheng_2022年国家公务员考试行测真题副省级_119",
    "module_id": "mod_data",
    "type": "single",
    "difficulty": "中等",
    "source": "国考真题",
    "year": 2022,
    "paper_id": "gk2022_fusheng_2022年国家公务员考试行测真题副省级",
    "paper_name": "2022年国家公务员考试《行测》真题（副省级)",
    "province": "国家",
    "position": "副省级",
    "paper_date": "",
    "question_number": 119,
    "content": "（单选题）2012—2020 年，中国IC 封装市场规模同比增量最大的年份是：",
    "stem_images": [],
    "material": "",
    "material_images": [
      "/assets/question-images/word-bank/gk2022_fusheng_2022年国家公务员考试行测真题副省级_0021_rId29.png"
    ],
    "options": [
      "2019 年",
      "2018 年",
      "2017 年",
      "2016 年"
    ],
    "option_images": [
      [],
      [],
      [],
      []
    ],
    "answer": 2,
    "explanation": "119.解析\n第一步，本题考查增长量做差比较。\n第二步，定位图形材料。\n第三步，根据增长量=现期量-基期量，本题是柱状图形式，要增长量最大，则柱状图高度差最大。观察可知，2017 年和2018 年的高度差最大，对两年进行做差比较，截三位，2017 年增长量：189-156=33，2018 年增长量：219-189=30，因此，同比增长量最大的是2017 年。\n因此，选择C 选项。",
    "explanation_images": [],
    "tags": [
      "资料分析"
    ],
    "status": "enabled"
  },
  {
    "_id": "q_gk2022_fusheng_2022年国家公务员考试行测真题副省级_121",
    "module_id": "mod_data",
    "type": "single",
    "difficulty": "中等",
    "source": "国考真题",
    "year": 2022,
    "paper_id": "gk2022_fusheng_2022年国家公务员考试行测真题副省级",
    "paper_name": "2022年国家公务员考试《行测》真题（副省级)",
    "province": "国家",
    "position": "副省级",
    "paper_date": "",
    "question_number": 121,
    "content": "（单选题）表中所列食品类别中，2021 年第一季度所有抽检样本全部合格的有几类？",
    "stem_images": [],
    "material": "",
    "material_images": [
      "/assets/question-images/word-bank/gk2022_fusheng_2022年国家公务员考试行测真题副省级_0022_rId30.png"
    ],
    "options": [
      "2",
      "3",
      "4",
      "5"
    ],
    "option_images": [
      [],
      [],
      [],
      []
    ],
    "answer": 1,
    "explanation": "121.解析\n第一步，本题考查简单比较中的读数比较。\n第二步，定位表格材料“抽检量”与“合格量”的数据。\n第三步，2021 年第一季度抽检样本全部合格，指的是抽检量=合格量，符合条件的有可可及焙烤咖啡产品（抽检量251，合格量251）、特殊医学用途配方食品（抽检量88，合格量88）、食品添加剂（抽检量112、合格量112），共3 个。\n因此，选择B 选项。",
    "explanation_images": [],
    "tags": [
      "资料分析"
    ],
    "status": "enabled"
  },
  {
    "_id": "q_gk2022_fusheng_2022年国家公务员考试行测真题副省级_122",
    "module_id": "mod_data",
    "type": "single",
    "difficulty": "中等",
    "source": "国考真题",
    "year": 2022,
    "paper_id": "gk2022_fusheng_2022年国家公务员考试行测真题副省级",
    "paper_name": "2022年国家公务员考试《行测》真题（副省级)",
    "province": "国家",
    "position": "副省级",
    "paper_date": "",
    "question_number": 122,
    "content": "（单选题）2021 年第一季度市场监管部门食品安全监督抽检的总体不合格率在以下哪个范围内？",
    "stem_images": [],
    "material": "",
    "material_images": [
      "/assets/question-images/word-bank/gk2022_fusheng_2022年国家公务员考试行测真题副省级_0022_rId30.png"
    ],
    "options": [
      "不到1%",
      "1%—2％之间",
      "2％—3％之间",
      "3％以上"
    ],
    "option_images": [
      [],
      [],
      [],
      []
    ],
    "answer": 2,
    "explanation": "122.解析\n第一步，本题考查现期比值计算。\n第二步，定位表格材料最后一行“合计”数据。\n第三步，不合格率= ，代入数据得 ，数据较大，分母从左向 右截取前三位，分子舍相同，得 。 因此，选择C 选项。",
    "explanation_images": [
      "/assets/question-images/word-bank/gk2022_fusheng_2022年国家公务员考试行测真题副省级_answer_0038_rId39.png",
      "/assets/question-images/word-bank/gk2022_fusheng_2022年国家公务员考试行测真题副省级_answer_0039_rId40.png",
      "/assets/question-images/word-bank/gk2022_fusheng_2022年国家公务员考试行测真题副省级_answer_0040_rId41.png"
    ],
    "tags": [
      "资料分析"
    ],
    "status": "enabled"
  },
  {
    "_id": "q_gk2022_fusheng_2022年国家公务员考试行测真题副省级_123",
    "module_id": "mod_data",
    "type": "single",
    "difficulty": "中等",
    "source": "国考真题",
    "year": 2022,
    "paper_id": "gk2022_fusheng_2022年国家公务员考试行测真题副省级",
    "paper_name": "2022年国家公务员考试《行测》真题（副省级)",
    "province": "国家",
    "position": "副省级",
    "paper_date": "",
    "question_number": 123,
    "content": "（单选题）2021 年第一季度市场监管部门食品安全监督抽检量最多的3 个食品类别，同期抽检不合格量\n约是其余所有类别抽检不合格量的多少倍？",
    "stem_images": [],
    "material": "",
    "material_images": [
      "/assets/question-images/word-bank/gk2022_fusheng_2022年国家公务员考试行测真题副省级_0022_rId30.png"
    ],
    "options": [
      "0.5",
      "0.8",
      "1.3",
      "1.9"
    ],
    "option_images": [
      [],
      [],
      [],
      []
    ],
    "answer": 3,
    "explanation": "123.解析\n第一步，本题考查现期倍数计算。\n第二步，定位表格材料。\n第三步，2021 年第一季度市场监管部门食品安全监督抽检量最多的三个食品类别是食用农产品（169040）、餐饮食品（37795）、粮食加工品（23131）。根据抽检不合格量=抽检量-合格量，食用农产品、餐饮食品、粮食加工品同期抽检不合格总量是（169040-164905）+（37795-35986）+（23131-22751），数据较大，将最大数据从左向右截取前三位，其余舍相同，得（169-165）+（38-36）+（23-23）=6，约是其余所有类别抽检不\n合格量的 倍，与D 选项最接近。 因此，选择D 选项。",
    "explanation_images": [
      "/assets/question-images/word-bank/gk2022_fusheng_2022年国家公务员考试行测真题副省级_answer_0041_rId42.png"
    ],
    "tags": [
      "资料分析"
    ],
    "status": "enabled"
  },
  {
    "_id": "q_gk2022_fusheng_2022年国家公务员考试行测真题副省级_124",
    "module_id": "mod_data",
    "type": "single",
    "difficulty": "中等",
    "source": "国考真题",
    "year": 2022,
    "paper_id": "gk2022_fusheng_2022年国家公务员考试行测真题副省级",
    "paper_name": "2022年国家公务员考试《行测》真题（副省级)",
    "province": "国家",
    "position": "副省级",
    "paper_date": "",
    "question_number": 124,
    "content": "（单选题）将①肉制品、②乳制品和③蛋制品按2021 年第一季度市场监管部门食品安全监督抽检合格率\n从高到低排列，以下正确的是：",
    "stem_images": [],
    "material": "",
    "material_images": [
      "/assets/question-images/word-bank/gk2022_fusheng_2022年国家公务员考试行测真题副省级_0022_rId30.png"
    ],
    "options": [
      "③②①",
      "②③①",
      "①②③",
      "①③②"
    ],
    "option_images": [
      [],
      [],
      [],
      []
    ],
    "answer": 1,
    "explanation": "124.解析\n第一步，本题考查现期比重比较。 第二步，定位表格材料。\n第三步，根据合格率=，比较类问题，截三位处理数据，可得①肉制品、②乳制品和③蛋制品的抽检合格\n第 61 页共 64 页\n率分别约为、、，直除首三位商分别983、998 和991，则从高到低排列为②③①。 因此，选择B 选项。",
    "explanation_images": [
      "/assets/question-images/word-bank/gk2022_fusheng_2022年国家公务员考试行测真题副省级_answer_0042_rId43.png",
      "/assets/question-images/word-bank/gk2022_fusheng_2022年国家公务员考试行测真题副省级_answer_0043_rId44.png",
      "/assets/question-images/word-bank/gk2022_fusheng_2022年国家公务员考试行测真题副省级_answer_0044_rId45.png",
      "/assets/question-images/word-bank/gk2022_fusheng_2022年国家公务员考试行测真题副省级_answer_0045_rId46.png"
    ],
    "tags": [
      "资料分析"
    ],
    "status": "enabled"
  },
  {
    "_id": "q_gk2022_fusheng_2022年国家公务员考试行测真题副省级_125",
    "module_id": "mod_data",
    "type": "single",
    "difficulty": "中等",
    "source": "国考真题",
    "year": 2022,
    "paper_id": "gk2022_fusheng_2022年国家公务员考试行测真题副省级",
    "paper_name": "2022年国家公务员考试《行测》真题（副省级)",
    "province": "国家",
    "position": "副省级",
    "paper_date": "",
    "question_number": 125,
    "content": "（单选题）关于2021 年第一季度市场监管部门食品安全监督情况，以下信息能够从上述资料中推出的有\n几项？\n①蔬菜、水果制品的总体抽检合格率高于95%\n②样品抽检量超过",
    "stem_images": [],
    "material": "",
    "material_images": [
      "/assets/question-images/word-bank/gk2022_fusheng_2022年国家公务员考试行测真题副省级_0022_rId30.png"
    ],
    "options": [
      "A",
      "B",
      "C",
      "D"
    ],
    "option_images": [
      [],
      [],
      [],
      []
    ],
    "answer": 0,
    "explanation": "125.解析\n第一步，本题考查综合分析问题，且需选出说法正确的一项。\n第二步，①，现期比值计算。定位表格材料，“蔬菜制品抽检量9241、合格量8598；水果制品抽检量5744、合\n格量5611”，根据抽检合格率= ，数据截取前三位，代入公式得 ，分母从左向右截 取前3 位， ，不到95%，错误。 ②，读数比较。定位表格材料，样品抽检量超过1 万批次的食品类别有粮食加工品（23131）、食用油、油脂及\n其制品（13879）、调味品（18862）、酒类（19091）、炒货食品及坚果制品（10678）、糕点（14517）、餐饮食品（37795）、食用农产品（169040）、肉制品（18104）、饮料（10515）、速冻食品（11620），合计11 个，错误。\n③，现期倍数计算。定位表格材料，糕点抽检量14517、合格量14214，则糕点类食品的抽检合格量是不合格量\n的 倍，分母四舍五入截取前三位，分子舍相同，得 ，错误。综上，正确 的有0 个。\n因此，选择A 选项。",
    "explanation_images": [
      "/assets/question-images/word-bank/gk2022_fusheng_2022年国家公务员考试行测真题副省级_answer_0046_rId43.png",
      "/assets/question-images/word-bank/gk2022_fusheng_2022年国家公务员考试行测真题副省级_answer_0047_rId47.png",
      "/assets/question-images/word-bank/gk2022_fusheng_2022年国家公务员考试行测真题副省级_answer_0048_rId48.png",
      "/assets/question-images/word-bank/gk2022_fusheng_2022年国家公务员考试行测真题副省级_answer_0049_rId49.png",
      "/assets/question-images/word-bank/gk2022_fusheng_2022年国家公务员考试行测真题副省级_answer_0050_rId50.png"
    ],
    "tags": [
      "资料分析"
    ],
    "status": "enabled"
  },
  {
    "_id": "q_gk2022_fusheng_2022年国家公务员考试行测真题副省级_126",
    "module_id": "mod_data",
    "type": "single",
    "difficulty": "中等",
    "source": "国考真题",
    "year": 2022,
    "paper_id": "gk2022_fusheng_2022年国家公务员考试行测真题副省级",
    "paper_name": "2022年国家公务员考试《行测》真题（副省级)",
    "province": "国家",
    "position": "副省级",
    "paper_date": "",
    "question_number": 126,
    "content": "（单选题）2019 年，H 省秋粮稻谷的平均生产成本约为多少元/亩？",
    "stem_images": [],
    "material": "几项？\n①蔬菜、水果制品的总体抽检合格率高于95%\n②样品抽检量超过",
    "material_images": [],
    "options": [
      "439",
      "450",
      "533",
      "548"
    ],
    "option_images": [
      [],
      [],
      [],
      []
    ],
    "answer": 3,
    "explanation": "126.解析\n第一步，本题考查基期量计算。\n第二步，定位表格可知“2020 年，H 省秋粮稻谷平均生产成本525.7 元/亩，同比下降4.0%”。\n第三步，根据公式，可得2019 年，秋粮稻谷平均生产成本为，根据丨－4%丨 ＜5%，利用公式法化除为乘，（元/亩），与D 选项最接近。\n因此，选择D 选项。",
    "explanation_images": [
      "/assets/question-images/word-bank/gk2022_fusheng_2022年国家公务员考试行测真题副省级_answer_0051_rId51.png",
      "/assets/question-images/word-bank/gk2022_fusheng_2022年国家公务员考试行测真题副省级_answer_0052_rId52.png",
      "/assets/question-images/word-bank/gk2022_fusheng_2022年国家公务员考试行测真题副省级_answer_0053_rId53.png"
    ],
    "tags": [
      "资料分析"
    ],
    "status": "enabled"
  },
  {
    "_id": "q_gk2022_fusheng_2022年国家公务员考试行测真题副省级_127",
    "module_id": "mod_data",
    "type": "single",
    "difficulty": "中等",
    "source": "国考真题",
    "year": 2022,
    "paper_id": "gk2022_fusheng_2022年国家公务员考试行测真题副省级",
    "paper_name": "2022年国家公务员考试《行测》真题（副省级)",
    "province": "国家",
    "position": "副省级",
    "paper_date": "",
    "question_number": 127,
    "content": "（单选题）将2020 年H 省秋粮机耕、机播、机收、排灌成本按同比增量从高到低的顺序排列，以下正确\n的是：",
    "stem_images": [],
    "material": "几项？\n①蔬菜、水果制品的总体抽检合格率高于95%\n②样品抽检量超过",
    "material_images": [],
    "options": [
      "机收、排灌、机耕、机播C.机耕、机播、排灌、机收",
      "机耕、机播、机收、排灌 D.机收、排灌、机播、机耕",
      "",
      ""
    ],
    "option_images": [
      [],
      [],
      [],
      []
    ],
    "answer": 1,
    "explanation": "127.解析\n第一步，本题考查增长量比较。\n第二步，定位表格可知“2020 年秋粮机耕成本22.1 元/亩，同比增长0.3%；机播成本21.7 元/亩，同比下降1.1%；机收成本62.3 元/亩，同比下降2.0%；排灌成本24.3 元/亩，同比下降12.0%”。\n第三步，由于机播成本、机收成本、排灌成本均比去年有所下降，故增量最高的是机耕成本，结合选项，排除A、D。分析B、C 可知，只需比较机收成本和排灌成本的增量即可，根据增长量比较口诀“大大则大，一大一小看乘积”，可知排灌成本现期量×增长率的绝对值较大，则排灌成本减少量高于机收成本减少量，故机收成本的增量高于排灌成本增量，排除C 选项。\n因此，选择B 选项。",
    "explanation_images": [],
    "tags": [
      "资料分析"
    ],
    "status": "enabled"
  },
  {
    "_id": "q_gk2022_fusheng_2022年国家公务员考试行测真题副省级_128",
    "module_id": "mod_data",
    "type": "single",
    "difficulty": "中等",
    "source": "国考真题",
    "year": 2022,
    "paper_id": "gk2022_fusheng_2022年国家公务员考试行测真题副省级",
    "paper_name": "2022年国家公务员考试《行测》真题（副省级)",
    "province": "国家",
    "position": "副省级",
    "paper_date": "",
    "question_number": 128,
    "content": "（单选题）2020 年，H 省秋粮玉米和稻谷的亩产与上年相比：",
    "stem_images": [],
    "material": "的是：",
    "material_images": [],
    "options": [
      "仅稻谷亩产高于上年水平C.两者亩产均高于上年水平",
      "仅玉米亩产高于上年水平 D.两者亩产均低于上年水平",
      "",
      ""
    ],
    "option_images": [
      [],
      [],
      [],
      []
    ],
    "answer": 2,
    "explanation": "128.解析\n第一步，本题考查两期平均数比较。\n第二步，定位文字材料“2020 年,H 省秋粮玉米和稻谷的市场平均交易价格分别为2.34 元/公斤和2.74 元/公斤，分别比上年上涨28.6%和8.7%。按此价格测算，2020 年全省农户种植玉米、稻谷扣除成本前的产值分别为957.1 元/亩、1520.7 元/亩，分别比上年增长33.4%，8.9%。” 第三步，亩产＝每亩产值/平均交易价格，根据两期平均数比较口诀，分子增速高于分母增速，平均数上升，反之\n第 62 页共 64 页\n则下降。2020 年秋粮玉米产值同比增速（33.4%）＞秋粮玉米平均交易价格同比增速（28.6%），则2020 年秋粮玉米亩产高于上年水平；2020 年秋粮稻谷产值同比增速（8.9%）＞秋粮稻谷平均交易价格同比增速（8.7%），则2020 年秋粮稻谷亩产高于上年水平，故两者亩产均高于上年水平。\n因此，选择C 选项。",
    "explanation_images": [],
    "tags": [
      "资料分析"
    ],
    "status": "enabled"
  },
  {
    "_id": "q_gk2022_fusheng_2022年国家公务员考试行测真题副省级_129",
    "module_id": "mod_data",
    "type": "single",
    "difficulty": "中等",
    "source": "国考真题",
    "year": 2022,
    "paper_id": "gk2022_fusheng_2022年国家公务员考试行测真题副省级",
    "paper_name": "2022年国家公务员考试《行测》真题（副省级)",
    "province": "国家",
    "position": "副省级",
    "paper_date": "",
    "question_number": 129,
    "content": "（单选题）如种植收益=产值－生产成本，则2020 年H 省秋粮稻谷平均每亩的种植收益约是玉米的多少\n倍？",
    "stem_images": [],
    "material": "的是：",
    "material_images": [],
    "options": [
      "1.9",
      "1.6",
      "0.7",
      "0.5"
    ],
    "option_images": [
      [],
      [],
      [],
      []
    ],
    "answer": 0,
    "explanation": "129.解析\n第一步，本题考查现期倍数计算。\n第二步，定位表格材料，秋粮稻谷生产成本为525.7 亿元，玉米生产成本为430.5 亿元；定位文字材料“2020 年全省农户种植玉米、稻谷扣除成本前的产值分别为957.1 元/亩、1520.7 元/亩”。\n第三步，根据种植收益=产值－生产成本以及倍数公式，选项首位相同第二位不同，分母从左向右截取前三位，分\n子减法计算考虑截位舍相同，代入数据可得，直除首两位商18，与A 选项最接近。 因此，选择A 选项。",
    "explanation_images": [
      "/assets/question-images/word-bank/gk2022_fusheng_2022年国家公务员考试行测真题副省级_answer_0054_rId54.png"
    ],
    "tags": [
      "资料分析"
    ],
    "status": "enabled"
  },
  {
    "_id": "q_gk2022_fusheng_2022年国家公务员考试行测真题副省级_131",
    "module_id": "mod_data",
    "type": "single",
    "difficulty": "中等",
    "source": "国考真题",
    "year": 2022,
    "paper_id": "gk2022_fusheng_2022年国家公务员考试行测真题副省级",
    "paper_name": "2022年国家公务员考试《行测》真题（副省级)",
    "province": "国家",
    "position": "副省级",
    "paper_date": "",
    "question_number": 131,
    "content": "（单选题）2021 年1 月，C 市天然气用量比上月：",
    "stem_images": [],
    "material": "的是：",
    "material_images": [],
    "options": [
      "增加了0.2 亿立方米以上C.减少了0.2 亿立方米以上",
      "减少了不到0.2 亿立方米 D.增加了不到0.2 亿立方米",
      "",
      ""
    ],
    "option_images": [
      [],
      [],
      [],
      []
    ],
    "answer": 0,
    "explanation": "131.解析\n第一步，本题考查简单计算中的和差类。\n第二步，定位文字材料第一、三、四段，“2020 年12 月，C 市天然气用量为9.67 亿立方米”“2021 年2 月，C 市天然气用量为9.31 亿立方米”“2021 年1—2 月，C 市天然气用量为19.21 亿立方米”。\n第三步，2021 年1 月=2021 年1—2 月-2021 年2 月，数据较为简单不再截位，直接代入计算，则2021 年1月C 市天然气用量为19.21-9.31=9.9 亿立方米。那么2021 年1 月C 市天然气用量比上月（2020 年12 月）增加了9.9-9.67=0.23 亿立方米，在A 选项范围内。\n因此，选择A 选项。",
    "explanation_images": [],
    "tags": [
      "资料分析"
    ],
    "status": "enabled"
  },
  {
    "_id": "q_gk2022_fusheng_2022年国家公务员考试行测真题副省级_132",
    "module_id": "mod_data",
    "type": "single",
    "difficulty": "中等",
    "source": "国考真题",
    "year": 2022,
    "paper_id": "gk2022_fusheng_2022年国家公务员考试行测真题副省级",
    "paper_name": "2022年国家公务员考试《行测》真题（副省级)",
    "province": "国家",
    "position": "副省级",
    "paper_date": "",
    "question_number": 132,
    "content": "（单选题）2020 年，中石化供气量占C 市天然气用量的比重比上年：",
    "stem_images": [],
    "material": "的是：",
    "material_images": [],
    "options": [
      "减少了不到3 个百分点C.减少了3 个百分点以上",
      "增加了不到3 个百分点 D.增加了3 个百分点以上",
      "",
      ""
    ],
    "option_images": [
      [],
      [],
      [],
      []
    ],
    "answer": 1,
    "explanation": "132.解析\n第一步，本题考查两期比重计算。\n第二步，定位文字材料第二段，“2020 年，C 市天然气用量为107.47 亿立方米，同比增长3.83%。其中……中石化供应33.51 立方米，同比增长8.8%”。\n第三步，根据两期比重比较口诀，部分增速a＞整体增速b，比重上升，反之则下降。中石化供气量同比增速a（8.8%）＞天然气用量同比增速b（3.83%），比重上升，排除A、C 选项。两期比重差应＜|a-b|=4.97%，不\n能排除选项。将数据简单取整，代入两期比重差公式 ，即增 加了不到3 个百分点。\n因此，选择B 选项。",
    "explanation_images": [
      "/assets/question-images/word-bank/gk2022_fusheng_2022年国家公务员考试行测真题副省级_answer_0057_rId57.png"
    ],
    "tags": [
      "资料分析"
    ],
    "status": "enabled"
  },
  {
    "_id": "q_gk2022_fusheng_2022年国家公务员考试行测真题副省级_133",
    "module_id": "mod_data",
    "type": "single",
    "difficulty": "中等",
    "source": "国考真题",
    "year": 2022,
    "paper_id": "gk2022_fusheng_2022年国家公务员考试行测真题副省级",
    "paper_name": "2022年国家公务员考试《行测》真题（副省级)",
    "province": "国家",
    "position": "副省级",
    "paper_date": "",
    "question_number": 133,
    "content": "（单选题）2019—2020 年，C 市CNG 用气总量约为多少亿立方米？",
    "stem_images": [],
    "material": "的是：",
    "material_images": [],
    "options": [
      "15",
      "17",
      "11",
      "13"
    ],
    "option_images": [
      [],
      [],
      [],
      []
    ],
    "answer": 0,
    "explanation": "133.解析\n第一步，本题考查基期量计算。\n第二步，定位文字材料第二段，“（2020 年C 市）CNG 用气6.99 亿立方米，同比下降13.92%”。\n第 63 页共 64 页\n第三步，根据基期量= ，选项数据首位相同，第二位不同，将分母从左向右截取前三位，代入可得 2019 年C 市CNG 用气总量约为亿立方米。则2019—2020 年，C 市CNG 用气总 量约为8.1+6.99≈15 亿立方米。\n因此，选择A 选项。",
    "explanation_images": [
      "/assets/question-images/word-bank/gk2022_fusheng_2022年国家公务员考试行测真题副省级_answer_0058_rId58.png",
      "/assets/question-images/word-bank/gk2022_fusheng_2022年国家公务员考试行测真题副省级_answer_0059_rId59.png"
    ],
    "tags": [
      "资料分析"
    ],
    "status": "enabled"
  },
  {
    "_id": "q_gk2022_fusheng_2022年国家公务员考试行测真题副省级_134",
    "module_id": "mod_data",
    "type": "single",
    "difficulty": "中等",
    "source": "国考真题",
    "year": 2022,
    "paper_id": "gk2022_fusheng_2022年国家公务员考试行测真题副省级",
    "paper_name": "2022年国家公务员考试《行测》真题（副省级)",
    "province": "国家",
    "position": "副省级",
    "paper_date": "",
    "question_number": 134,
    "content": "（单选题）以下哪个饼图最能准确反映2021 年1—2 月C 市天然气用量中，民用气（白色）、CNG 用气（黑色）和工业用气（斜线）的占比关系？",
    "stem_images": [
      "/assets/question-images/word-bank/gk2022_fusheng_2022年国家公务员考试行测真题副省级_0024_rId32.png"
    ],
    "material": "的是：",
    "material_images": [],
    "options": [
      "如上图所示",
      "如上图所示",
      "如上图所示",
      "如上图所示"
    ],
    "option_images": [
      [],
      [],
      [],
      []
    ],
    "answer": 3,
    "explanation": "134.解析\n第一步，本题考查比重比较。\n第二步，定位文字材料最后一段，“2021 年1—2 月，C 市天然气用量为19.21 亿立方米……从用气结构看：民用气为7.78 亿立方米，同比增长12.75%；CNG 用气1.14 亿立方米，同比增长44.3%；工业用气10.29 亿立方米，同比增长10.17%”。\n第三步，首先根据民用气用量（7.78）和工业用气用量（10.29）相差不到1 倍，排除A、C 选项；其次根据民用气用量少于工业用气用量，排除B 选项。\n因此，选择D 选项。",
    "explanation_images": [],
    "tags": [
      "资料分析"
    ],
    "status": "enabled"
  },
  {
    "_id": "q_gk2022_fusheng_2022年国家公务员考试行测真题副省级_135",
    "module_id": "mod_data",
    "type": "single",
    "difficulty": "中等",
    "source": "国考真题",
    "year": 2022,
    "paper_id": "gk2022_fusheng_2022年国家公务员考试行测真题副省级",
    "paper_name": "2022年国家公务员考试《行测》真题（副省级)",
    "province": "国家",
    "position": "副省级",
    "paper_date": "",
    "question_number": 135,
    "content": "（单选题）以下柱状图反映了C 市天然气2020 年12 月—2021 年2 月间哪一数值的变化趋势？",
    "stem_images": [
      "/assets/question-images/word-bank/gk2022_fusheng_2022年国家公务员考试行测真题副省级_0025_rId33.png"
    ],
    "material": "",
    "material_images": [
      "/assets/question-images/word-bank/gk2022_fusheng_2022年国家公务员考试行测真题副省级_0024_rId32.png"
    ],
    "options": [
      "中石油供气量",
      "中石化供气量",
      "民用气用量",
      "工业用气用量"
    ],
    "option_images": [
      [],
      [],
      [],
      []
    ],
    "answer": 1,
    "explanation": "135.解析\n第一步 ，本题考查和差比较。\n第二步，定位文字材料第一、三、四段。\n第三步，A 选项，中石油：2021 年1 月供气量为14.23－6.7＝7.53 亿立方米，2 月供气量为6.7 亿立方米，与柱状图中1 月数值小于2 月数值不符，排除；B 选项，中石化：2020 年1 月供气量为4.98－2.61＝2.37 亿立方米，2 月供气量为2.61 亿立方米，2020 年12 月供气量为2.45 亿立方米，符合柱状图趋势；C 选项，民用气：2021 年1 月用量为7.78－3.56＝4.22 亿立方米，2 月用量为3.56 亿立方米，与柱状图不符，排除；D 选项，工业用气：2021 年1 月用量为10.29－5.23＝5.06 亿立方米，2 月用量为5.23 亿立方米，2020 年12 月用量为5.05 亿立方米，与柱状图不符，排除。\n因此，选择B 选项。\n第 64 页共 64 页",
    "explanation_images": [],
    "tags": [
      "资料分析"
    ],
    "status": "enabled"
  }
]